pyncei/__init__.py
pyncei/bot.py
pyncei/files/datacategories.csv
pyncei/files/datasets.csv
pyncei/files/datatypes.csv
pyncei/files/locationcategories.csv
pyncei/files/locations.csv
pyncei-1.0.dist-info/METADATA
pyncei-1.0.dist-info/WHEEL
pyncei-1.0.dist-info/top_level.txt
pyncei-1.0.dist-info/RECORD
